nbs_gui/__init__.py
nbs_gui/confEdit.py
nbs_gui/load.py
nbs_gui/main.py
nbs_gui/mainWidget.py
nbs_gui/model.py
nbs_gui/settings.py
nbs_gui/testScaffolding.py
nbs_gui/window.py
nbs_gui/models/QtReQueueStaging.py
nbs_gui/models/QtRedisJSONDict.py
nbs_gui/models/__init__.py
nbs_gui/models/base.py
nbs_gui/models/beamline.py
nbs_gui/models/misc.py
nbs_gui/models/mixins.py
nbs_gui/models/mode.py
nbs_gui/models/motors.py
nbs_gui/models/redis.py
nbs_gui/models/signal_tuple.py
nbs_gui/models/userStatus.py
nbs_gui/plans/__init__.py
nbs_gui/plans/autoPlanWidget.py
nbs_gui/plans/base.py
nbs_gui/plans/commentWidget.py
nbs_gui/plans/conditionMetaPlan.py
nbs_gui/plans/durationMetaPlan.py
nbs_gui/plans/flyscanPlan.py
nbs_gui/plans/metaPlanBase.py
nbs_gui/plans/movePlan.py
nbs_gui/plans/nbsPlan.py
nbs_gui/plans/planLoaders.py
nbs_gui/plans/planParam.py
nbs_gui/plans/sampleModifier.py
nbs_gui/plans/sampleMovePlan.py
nbs_gui/plans/scanModifier.py
nbs_gui/plans/scanPlan.py
nbs_gui/plans/variableStepPlan.py
nbs_gui/plans/xasPlan.py
nbs_gui/tabs/__init__.py
nbs_gui/tabs/consoleTab.py
nbs_gui/tabs/monitorTab.py
nbs_gui/tabs/motorTab.py
nbs_gui/tabs/queueControlTab.py
nbs_gui/tabs/sampleTab.py
nbs_gui/views/energy.py
nbs_gui/views/enums.py
nbs_gui/views/gatevalve.py
nbs_gui/views/manipulator_monitor.py
nbs_gui/views/mixins.py
nbs_gui/views/mode.py
nbs_gui/views/monitors.py
nbs_gui/views/motor.py
nbs_gui/views/motor_tuple.py
nbs_gui/views/signal_tuple.py
nbs_gui/views/status.py
nbs_gui/views/switchable_motors.py
nbs_gui/views/views.py
nbs_gui/widgets/QtRePlanQueueBase.py
nbs_gui/widgets/QtReQueueStaging.py
nbs_gui/widgets/QtReRunningPlan.py
nbs_gui/widgets/__init__.py
nbs_gui/widgets/header.py
nbs_gui/widgets/metaPlanSubmission.py
nbs_gui/widgets/mode_managed.py
nbs_gui/widgets/planControl.py
nbs_gui/widgets/planEditor.py
nbs_gui/widgets/planSubmission.py
nbs_gui/widgets/qt_custom.py
nbs_gui/widgets/queueControl.py
nbs_gui/widgets/sampleSelect.py
nbs_gui/widgets/serverControl.py
nbs_gui-0.1.2.dist-info/METADATA
nbs_gui-0.1.2.dist-info/WHEEL
nbs_gui-0.1.2.dist-info/entry_points.txt
nbs_gui-0.1.2.dist-info/licenses/LICENSE
nbs_gui-0.1.2.dist-info/RECORD
