Metadata-Version: 2.4
Name: nbs-gui
Version: 0.1.2
Summary: NBS GUI Module
Project-URL: homepage, https://github.com/xraygui/nbs-gui
Author-email: Charles Titus <ctitus@bnl.gov>
License-File: LICENSE
Keywords: bluesky,gui,nsls-ii
Classifier: Intended Audience :: Science/Research
Classifier: License :: Public Domain
Classifier: Operating System :: OS Independent
Classifier: Programming Language :: Python :: 3
Requires-Python: >=3.8
Requires-Dist: bluesky-queueserver-api
Requires-Dist: bluesky-widgets<0.0.18,>=0.0.17
Requires-Dist: nbs-bl>=0.2
Requires-Dist: nbs-core>=0.1
Requires-Dist: ophyd
Requires-Dist: qtpy
Requires-Dist: tomli-w
Requires-Dist: tomli; python_version < '3.11'
